{
  "namespaces": ["public"],
  "name": "public",
  "tables": [
    {
      "columns": {
        "id": {
          "name": "id",
          "type": "serial",
          "unsigned": true,
          "autoincrement": true,
          "primary": true,
          "nullable": false,
          "mappedType": "integer"
        },
        "created_at": {
          "name": "created_at",
          "type": "timestamptz",
          "unsigned": false,
          "autoincrement": false,
          "primary": false,
          "nullable": false,
          "length": 6,
          "mappedType": "datetime"
        },
        "updated_at": {
          "name": "updated_at",
          "type": "timestamptz",
          "unsigned": false,
          "autoincrement": false,
          "primary": false,
          "nullable": false,
          "length": 6,
          "mappedType": "datetime"
        },
        "idx": {
          "name": "idx",
          "type": "varchar(255)",
          "unsigned": false,
          "autoincrement": false,
          "primary": false,
          "nullable": false,
          "mappedType": "string"
        },
        "revision": {
          "name": "revision",
          "type": "int",
          "unsigned": false,
          "autoincrement": false,
          "primary": false,
          "nullable": false,
          "default": "0",
          "mappedType": "integer"
        },
        "is_deleted": {
          "name": "is_deleted",
          "type": "boolean",
          "unsigned": false,
          "autoincrement": false,
          "primary": false,
          "nullable": false,
          "default": "false",
          "mappedType": "boolean"
        },
        "deleted_at": {
          "name": "deleted_at",
          "type": "timestamptz",
          "unsigned": false,
          "autoincrement": false,
          "primary": false,
          "nullable": true,
          "length": 6,
          "default": "null",
          "mappedType": "datetime"
        },
        "name": {
          "name": "name",
          "type": "varchar(255)",
          "unsigned": false,
          "autoincrement": false,
          "primary": false,
          "nullable": false,
          "mappedType": "string"
        },
        "description": {
          "name": "description",
          "type": "varchar(255)",
          "unsigned": false,
          "autoincrement": false,
          "primary": false,
          "nullable": false,
          "mappedType": "string"
        }
      },
      "name": "role",
      "schema": "public",
      "indexes": [
        {
          "columnNames": ["id"],
          "composite": false,
          "keyName": "role_id_index",
          "constraint": false,
          "primary": false,
          "unique": false
        },
        {
          "columnNames": ["idx"],
          "composite": false,
          "keyName": "role_idx_index",
          "constraint": false,
          "primary": false,
          "unique": false
        },
        {
          "columnNames": ["is_deleted"],
          "composite": false,
          "keyName": "role_is_deleted_index",
          "constraint": false,
          "primary": false,
          "unique": false
        },
        {
          "columnNames": ["deleted_at"],
          "composite": false,
          "keyName": "role_deleted_at_index",
          "constraint": false,
          "primary": false,
          "unique": false
        },
        {
          "columnNames": ["name"],
          "composite": false,
          "keyName": "role_name_index",
          "constraint": false,
          "primary": false,
          "unique": false
        },
        {
          "columnNames": ["name"],
          "composite": false,
          "keyName": "role_name_unique",
          "constraint": true,
          "primary": false,
          "unique": true
        },
        {
          "keyName": "role_pkey",
          "columnNames": ["id"],
          "composite": false,
          "constraint": true,
          "primary": true,
          "unique": true
        }
      ],
      "checks": [],
      "foreignKeys": {},
      "nativeEnums": {}
    },
    {
      "columns": {
        "id": {
          "name": "id",
          "type": "serial",
          "unsigned": true,
          "autoincrement": true,
          "primary": true,
          "nullable": false,
          "mappedType": "integer"
        },
        "created_at": {
          "name": "created_at",
          "type": "timestamptz",
          "unsigned": false,
          "autoincrement": false,
          "primary": false,
          "nullable": false,
          "length": 6,
          "mappedType": "datetime"
        },
        "updated_at": {
          "name": "updated_at",
          "type": "timestamptz",
          "unsigned": false,
          "autoincrement": false,
          "primary": false,
          "nullable": false,
          "length": 6,
          "mappedType": "datetime"
        },
        "name": {
          "name": "name",
          "type": "varchar(255)",
          "unsigned": false,
          "autoincrement": false,
          "primary": false,
          "nullable": false,
          "mappedType": "string"
        }
      },
      "name": "service_type",
      "schema": "public",
      "indexes": [
        {
          "columnNames": ["id"],
          "composite": false,
          "keyName": "service_type_id_index",
          "constraint": false,
          "primary": false,
          "unique": false
        },
        {
          "columnNames": ["name"],
          "composite": false,
          "keyName": "service_type_name_index",
          "constraint": false,
          "primary": false,
          "unique": false
        },
        {
          "columnNames": ["name"],
          "composite": false,
          "keyName": "service_type_name_unique",
          "constraint": true,
          "primary": false,
          "unique": true
        },
        {
          "keyName": "service_type_pkey",
          "columnNames": ["id"],
          "composite": false,
          "constraint": true,
          "primary": true,
          "unique": true
        }
      ],
      "checks": [],
      "foreignKeys": {},
      "nativeEnums": {}
    },
    {
      "columns": {
        "id": {
          "name": "id",
          "type": "serial",
          "unsigned": true,
          "autoincrement": true,
          "primary": true,
          "nullable": false,
          "mappedType": "integer"
        },
        "scope": {
          "name": "scope",
          "type": "varchar(255)",
          "unsigned": false,
          "autoincrement": false,
          "primary": false,
          "nullable": false,
          "mappedType": "string"
        },
        "properties": {
          "name": "properties",
          "type": "jsonb",
          "unsigned": false,
          "autoincrement": false,
          "primary": false,
          "nullable": false,
          "mappedType": "json"
        }
      },
      "name": "system",
      "schema": "public",
      "indexes": [
        {
          "keyName": "system_pkey",
          "columnNames": ["id"],
          "composite": false,
          "constraint": true,
          "primary": true,
          "unique": true
        }
      ],
      "checks": [],
      "foreignKeys": {},
      "nativeEnums": {}
    },
    {
      "columns": {
        "id": {
          "name": "id",
          "type": "serial",
          "unsigned": true,
          "autoincrement": true,
          "primary": true,
          "nullable": false,
          "mappedType": "integer"
        },
        "created_at": {
          "name": "created_at",
          "type": "timestamptz",
          "unsigned": false,
          "autoincrement": false,
          "primary": false,
          "nullable": false,
          "length": 6,
          "mappedType": "datetime"
        },
        "updated_at": {
          "name": "updated_at",
          "type": "timestamptz",
          "unsigned": false,
          "autoincrement": false,
          "primary": false,
          "nullable": false,
          "length": 6,
          "mappedType": "datetime"
        },
        "idx": {
          "name": "idx",
          "type": "varchar(255)",
          "unsigned": false,
          "autoincrement": false,
          "primary": false,
          "nullable": false,
          "mappedType": "string"
        },
        "revision": {
          "name": "revision",
          "type": "int",
          "unsigned": false,
          "autoincrement": false,
          "primary": false,
          "nullable": false,
          "default": "0",
          "mappedType": "integer"
        },
        "is_deleted": {
          "name": "is_deleted",
          "type": "boolean",
          "unsigned": false,
          "autoincrement": false,
          "primary": false,
          "nullable": false,
          "default": "false",
          "mappedType": "boolean"
        },
        "deleted_at": {
          "name": "deleted_at",
          "type": "timestamptz",
          "unsigned": false,
          "autoincrement": false,
          "primary": false,
          "nullable": true,
          "length": 6,
          "default": "null",
          "mappedType": "datetime"
        },
        "email": {
          "name": "email",
          "type": "varchar(255)",
          "unsigned": false,
          "autoincrement": false,
          "primary": false,
          "nullable": false,
          "mappedType": "string"
        },
        "name": {
          "name": "name",
          "type": "text",
          "unsigned": false,
          "autoincrement": false,
          "primary": false,
          "nullable": false,
          "mappedType": "text"
        },
        "roles": {
          "name": "roles",
          "type": "text[]",
          "unsigned": false,
          "autoincrement": false,
          "primary": false,
          "nullable": true,
          "mappedType": "array"
        },
        "roles_override": {
          "name": "roles_override",
          "type": "text[]",
          "unsigned": false,
          "autoincrement": false,
          "primary": false,
          "nullable": true,
          "mappedType": "array"
        },
        "kube_config": {
          "name": "kube_config",
          "type": "text",
          "unsigned": false,
          "autoincrement": false,
          "primary": false,
          "nullable": true,
          "mappedType": "text"
        }
      },
      "name": "user",
      "schema": "public",
      "indexes": [
        {
          "columnNames": ["id"],
          "composite": false,
          "keyName": "user_id_index",
          "constraint": false,
          "primary": false,
          "unique": false
        },
        {
          "columnNames": ["idx"],
          "composite": false,
          "keyName": "user_idx_index",
          "constraint": false,
          "primary": false,
          "unique": false
        },
        {
          "columnNames": ["is_deleted"],
          "composite": false,
          "keyName": "user_is_deleted_index",
          "constraint": false,
          "primary": false,
          "unique": false
        },
        {
          "columnNames": ["deleted_at"],
          "composite": false,
          "keyName": "user_deleted_at_index",
          "constraint": false,
          "primary": false,
          "unique": false
        },
        {
          "columnNames": ["email"],
          "composite": false,
          "keyName": "user_email_index",
          "constraint": false,
          "primary": false,
          "unique": false
        },
        {
          "columnNames": ["email"],
          "composite": false,
          "keyName": "user_email_unique",
          "constraint": true,
          "primary": false,
          "unique": true
        },
        {
          "keyName": "user_pkey",
          "columnNames": ["id"],
          "composite": false,
          "constraint": true,
          "primary": true,
          "unique": true
        }
      ],
      "checks": [],
      "foreignKeys": {},
      "nativeEnums": {}
    },
    {
      "columns": {
        "id": {
          "name": "id",
          "type": "serial",
          "unsigned": true,
          "autoincrement": true,
          "primary": true,
          "nullable": false,
          "mappedType": "integer"
        },
        "created_at": {
          "name": "created_at",
          "type": "timestamptz",
          "unsigned": false,
          "autoincrement": false,
          "primary": false,
          "nullable": false,
          "length": 6,
          "mappedType": "datetime"
        },
        "updated_at": {
          "name": "updated_at",
          "type": "timestamptz",
          "unsigned": false,
          "autoincrement": false,
          "primary": false,
          "nullable": false,
          "length": 6,
          "mappedType": "datetime"
        },
        "idx": {
          "name": "idx",
          "type": "varchar(255)",
          "unsigned": false,
          "autoincrement": false,
          "primary": false,
          "nullable": false,
          "mappedType": "string"
        },
        "revision": {
          "name": "revision",
          "type": "int",
          "unsigned": false,
          "autoincrement": false,
          "primary": false,
          "nullable": false,
          "default": "0",
          "mappedType": "integer"
        },
        "is_deleted": {
          "name": "is_deleted",
          "type": "boolean",
          "unsigned": false,
          "autoincrement": false,
          "primary": false,
          "nullable": false,
          "default": "false",
          "mappedType": "boolean"
        },
        "deleted_at": {
          "name": "deleted_at",
          "type": "timestamptz",
          "unsigned": false,
          "autoincrement": false,
          "primary": false,
          "nullable": true,
          "length": 6,
          "default": "null",
          "mappedType": "datetime"
        },
        "name": {
          "name": "name",
          "type": "varchar(255)",
          "unsigned": false,
          "autoincrement": false,
          "primary": false,
          "nullable": false,
          "mappedType": "string"
        },
        "description": {
          "name": "description",
          "type": "varchar(255)",
          "unsigned": false,
          "autoincrement": false,
          "primary": false,
          "nullable": false,
          "mappedType": "string"
        },
        "user_id": {
          "name": "user_id",
          "type": "int",
          "unsigned": false,
          "autoincrement": false,
          "primary": false,
          "nullable": false,
          "mappedType": "integer"
        },
        "is_active": {
          "name": "is_active",
          "type": "boolean",
          "unsigned": false,
          "autoincrement": false,
          "primary": false,
          "nullable": false,
          "default": "false",
          "mappedType": "boolean"
        }
      },
      "name": "structure",
      "schema": "public",
      "indexes": [
        {
          "columnNames": ["id"],
          "composite": false,
          "keyName": "structure_id_index",
          "constraint": false,
          "primary": false,
          "unique": false
        },
        {
          "columnNames": ["idx"],
          "composite": false,
          "keyName": "structure_idx_index",
          "constraint": false,
          "primary": false,
          "unique": false
        },
        {
          "columnNames": ["is_deleted"],
          "composite": false,
          "keyName": "structure_is_deleted_index",
          "constraint": false,
          "primary": false,
          "unique": false
        },
        {
          "columnNames": ["deleted_at"],
          "composite": false,
          "keyName": "structure_deleted_at_index",
          "constraint": false,
          "primary": false,
          "unique": false
        },
        {
          "columnNames": ["is_active"],
          "composite": false,
          "keyName": "structure_is_active_index",
          "constraint": false,
          "primary": false,
          "unique": false
        },
        {
          "keyName": "structure_name_revision_unique",
          "columnNames": ["name", "revision"],
          "composite": true,
          "constraint": true,
          "primary": false,
          "unique": true
        },
        {
          "keyName": "structure_pkey",
          "columnNames": ["id"],
          "composite": false,
          "constraint": true,
          "primary": true,
          "unique": true
        }
      ],
      "checks": [],
      "foreignKeys": {
        "structure_user_id_foreign": {
          "constraintName": "structure_user_id_foreign",
          "columnNames": ["user_id"],
          "localTableName": "public.structure",
          "referencedColumnNames": ["id"],
          "referencedTableName": "public.user",
          "updateRule": "cascade"
        }
      },
      "nativeEnums": {}
    },
    {
      "columns": {
        "id": {
          "name": "id",
          "type": "serial",
          "unsigned": true,
          "autoincrement": true,
          "primary": true,
          "nullable": false,
          "mappedType": "integer"
        },
        "created_at": {
          "name": "created_at",
          "type": "timestamptz",
          "unsigned": false,
          "autoincrement": false,
          "primary": false,
          "nullable": false,
          "length": 6,
          "mappedType": "datetime"
        },
        "updated_at": {
          "name": "updated_at",
          "type": "timestamptz",
          "unsigned": false,
          "autoincrement": false,
          "primary": false,
          "nullable": false,
          "length": 6,
          "mappedType": "datetime"
        },
        "idx": {
          "name": "idx",
          "type": "varchar(255)",
          "unsigned": false,
          "autoincrement": false,
          "primary": false,
          "nullable": false,
          "mappedType": "string"
        },
        "revision": {
          "name": "revision",
          "type": "int",
          "unsigned": false,
          "autoincrement": false,
          "primary": false,
          "nullable": false,
          "default": "0",
          "mappedType": "integer"
        },
        "is_deleted": {
          "name": "is_deleted",
          "type": "boolean",
          "unsigned": false,
          "autoincrement": false,
          "primary": false,
          "nullable": false,
          "default": "false",
          "mappedType": "boolean"
        },
        "deleted_at": {
          "name": "deleted_at",
          "type": "timestamptz",
          "unsigned": false,
          "autoincrement": false,
          "primary": false,
          "nullable": true,
          "length": 6,
          "default": "null",
          "mappedType": "datetime"
        },
        "name": {
          "name": "name",
          "type": "varchar(255)",
          "unsigned": false,
          "autoincrement": false,
          "primary": false,
          "nullable": false,
          "mappedType": "string"
        },
        "pattern": {
          "name": "pattern",
          "type": "jsonb",
          "unsigned": false,
          "autoincrement": false,
          "primary": false,
          "nullable": false,
          "mappedType": "json"
        },
        "user_id": {
          "name": "user_id",
          "type": "int",
          "unsigned": false,
          "autoincrement": false,
          "primary": false,
          "nullable": false,
          "mappedType": "integer"
        }
      },
      "name": "setting_type",
      "schema": "public",
      "indexes": [
        {
          "columnNames": ["id"],
          "composite": false,
          "keyName": "setting_type_id_index",
          "constraint": false,
          "primary": false,
          "unique": false
        },
        {
          "columnNames": ["idx"],
          "composite": false,
          "keyName": "setting_type_idx_index",
          "constraint": false,
          "primary": false,
          "unique": false
        },
        {
          "columnNames": ["is_deleted"],
          "composite": false,
          "keyName": "setting_type_is_deleted_index",
          "constraint": false,
          "primary": false,
          "unique": false
        },
        {
          "columnNames": ["deleted_at"],
          "composite": false,
          "keyName": "setting_type_deleted_at_index",
          "constraint": false,
          "primary": false,
          "unique": false
        },
        {
          "columnNames": ["name"],
          "composite": false,
          "keyName": "setting_type_name_index",
          "constraint": false,
          "primary": false,
          "unique": false
        },
        {
          "columnNames": ["name"],
          "composite": false,
          "keyName": "setting_type_name_unique",
          "constraint": true,
          "primary": false,
          "unique": true
        },
        {
          "keyName": "setting_type_pkey",
          "columnNames": ["id"],
          "composite": false,
          "constraint": true,
          "primary": true,
          "unique": true
        }
      ],
      "checks": [],
      "foreignKeys": {
        "setting_type_user_id_foreign": {
          "constraintName": "setting_type_user_id_foreign",
          "columnNames": ["user_id"],
          "localTableName": "public.setting_type",
          "referencedColumnNames": ["id"],
          "referencedTableName": "public.user",
          "updateRule": "cascade"
        }
      },
      "nativeEnums": {}
    },
    {
      "columns": {
        "id": {
          "name": "id",
          "type": "serial",
          "unsigned": true,
          "autoincrement": true,
          "primary": true,
          "nullable": false,
          "mappedType": "integer"
        },
        "created_at": {
          "name": "created_at",
          "type": "timestamptz",
          "unsigned": false,
          "autoincrement": false,
          "primary": false,
          "nullable": false,
          "length": 6,
          "mappedType": "datetime"
        },
        "updated_at": {
          "name": "updated_at",
          "type": "timestamptz",
          "unsigned": false,
          "autoincrement": false,
          "primary": false,
          "nullable": false,
          "length": 6,
          "mappedType": "datetime"
        },
        "idx": {
          "name": "idx",
          "type": "varchar(255)",
          "unsigned": false,
          "autoincrement": false,
          "primary": false,
          "nullable": false,
          "mappedType": "string"
        },
        "revision": {
          "name": "revision",
          "type": "int",
          "unsigned": false,
          "autoincrement": false,
          "primary": false,
          "nullable": false,
          "default": "0",
          "mappedType": "integer"
        },
        "is_deleted": {
          "name": "is_deleted",
          "type": "boolean",
          "unsigned": false,
          "autoincrement": false,
          "primary": false,
          "nullable": false,
          "default": "false",
          "mappedType": "boolean"
        },
        "deleted_at": {
          "name": "deleted_at",
          "type": "timestamptz",
          "unsigned": false,
          "autoincrement": false,
          "primary": false,
          "nullable": true,
          "length": 6,
          "default": "null",
          "mappedType": "datetime"
        },
        "type_id": {
          "name": "type_id",
          "type": "int",
          "unsigned": false,
          "autoincrement": false,
          "primary": false,
          "nullable": false,
          "mappedType": "integer"
        },
        "extends": {
          "name": "extends",
          "type": "text[]",
          "unsigned": false,
          "autoincrement": false,
          "primary": false,
          "nullable": false,
          "mappedType": "array"
        },
        "properties": {
          "name": "properties",
          "type": "jsonb",
          "unsigned": false,
          "autoincrement": false,
          "primary": false,
          "nullable": false,
          "mappedType": "json"
        },
        "user_id": {
          "name": "user_id",
          "type": "int",
          "unsigned": false,
          "autoincrement": false,
          "primary": false,
          "nullable": false,
          "mappedType": "integer"
        }
      },
      "name": "setting",
      "schema": "public",
      "indexes": [
        {
          "columnNames": ["id"],
          "composite": false,
          "keyName": "setting_id_index",
          "constraint": false,
          "primary": false,
          "unique": false
        },
        {
          "columnNames": ["idx"],
          "composite": false,
          "keyName": "setting_idx_index",
          "constraint": false,
          "primary": false,
          "unique": false
        },
        {
          "columnNames": ["is_deleted"],
          "composite": false,
          "keyName": "setting_is_deleted_index",
          "constraint": false,
          "primary": false,
          "unique": false
        },
        {
          "columnNames": ["deleted_at"],
          "composite": false,
          "keyName": "setting_deleted_at_index",
          "constraint": false,
          "primary": false,
          "unique": false
        },
        {
          "keyName": "setting_pkey",
          "columnNames": ["id"],
          "composite": false,
          "constraint": true,
          "primary": true,
          "unique": true
        }
      ],
      "checks": [],
      "foreignKeys": {
        "setting_type_id_foreign": {
          "constraintName": "setting_type_id_foreign",
          "columnNames": ["type_id"],
          "localTableName": "public.setting",
          "referencedColumnNames": ["id"],
          "referencedTableName": "public.setting_type",
          "updateRule": "cascade"
        },
        "setting_user_id_foreign": {
          "constraintName": "setting_user_id_foreign",
          "columnNames": ["user_id"],
          "localTableName": "public.setting",
          "referencedColumnNames": ["id"],
          "referencedTableName": "public.user",
          "updateRule": "cascade"
        }
      },
      "nativeEnums": {}
    },
    {
      "columns": {
        "structure_id": {
          "name": "structure_id",
          "type": "int",
          "unsigned": false,
          "autoincrement": false,
          "primary": false,
          "nullable": false,
          "mappedType": "integer"
        },
        "setting_id": {
          "name": "setting_id",
          "type": "int",
          "unsigned": false,
          "autoincrement": false,
          "primary": false,
          "nullable": false,
          "mappedType": "integer"
        }
      },
      "name": "structure_settings",
      "schema": "public",
      "indexes": [
        {
          "keyName": "structure_settings_pkey",
          "columnNames": ["structure_id", "setting_id"],
          "composite": true,
          "constraint": true,
          "primary": true,
          "unique": true
        }
      ],
      "checks": [],
      "foreignKeys": {
        "structure_settings_structure_id_foreign": {
          "constraintName": "structure_settings_structure_id_foreign",
          "columnNames": ["structure_id"],
          "localTableName": "public.structure_settings",
          "referencedColumnNames": ["id"],
          "referencedTableName": "public.structure",
          "deleteRule": "cascade",
          "updateRule": "cascade"
        },
        "structure_settings_setting_id_foreign": {
          "constraintName": "structure_settings_setting_id_foreign",
          "columnNames": ["setting_id"],
          "localTableName": "public.structure_settings",
          "referencedColumnNames": ["id"],
          "referencedTableName": "public.setting",
          "deleteRule": "cascade",
          "updateRule": "cascade"
        }
      },
      "nativeEnums": {}
    },
    {
      "columns": {
        "id": {
          "name": "id",
          "type": "serial",
          "unsigned": true,
          "autoincrement": true,
          "primary": true,
          "nullable": false,
          "mappedType": "integer"
        },
        "created_at": {
          "name": "created_at",
          "type": "timestamptz",
          "unsigned": false,
          "autoincrement": false,
          "primary": false,
          "nullable": false,
          "length": 6,
          "mappedType": "datetime"
        },
        "updated_at": {
          "name": "updated_at",
          "type": "timestamptz",
          "unsigned": false,
          "autoincrement": false,
          "primary": false,
          "nullable": false,
          "length": 6,
          "mappedType": "datetime"
        },
        "idx": {
          "name": "idx",
          "type": "varchar(255)",
          "unsigned": false,
          "autoincrement": false,
          "primary": false,
          "nullable": false,
          "mappedType": "string"
        },
        "revision": {
          "name": "revision",
          "type": "int",
          "unsigned": false,
          "autoincrement": false,
          "primary": false,
          "nullable": false,
          "default": "0",
          "mappedType": "integer"
        },
        "is_deleted": {
          "name": "is_deleted",
          "type": "boolean",
          "unsigned": false,
          "autoincrement": false,
          "primary": false,
          "nullable": false,
          "default": "false",
          "mappedType": "boolean"
        },
        "deleted_at": {
          "name": "deleted_at",
          "type": "timestamptz",
          "unsigned": false,
          "autoincrement": false,
          "primary": false,
          "nullable": true,
          "length": 6,
          "default": "null",
          "mappedType": "datetime"
        },
        "name": {
          "name": "name",
          "type": "varchar(255)",
          "unsigned": false,
          "autoincrement": false,
          "primary": false,
          "nullable": false,
          "mappedType": "string"
        },
        "description": {
          "name": "description",
          "type": "varchar(255)",
          "unsigned": false,
          "autoincrement": false,
          "primary": false,
          "nullable": false,
          "mappedType": "string"
        },
        "type_id": {
          "name": "type_id",
          "type": "int",
          "unsigned": false,
          "autoincrement": false,
          "primary": false,
          "nullable": false,
          "mappedType": "integer"
        },
        "user_id": {
          "name": "user_id",
          "type": "int",
          "unsigned": false,
          "autoincrement": false,
          "primary": false,
          "nullable": false,
          "mappedType": "integer"
        }
      },
      "name": "service",
      "schema": "public",
      "indexes": [
        {
          "columnNames": ["id"],
          "composite": false,
          "keyName": "service_id_index",
          "constraint": false,
          "primary": false,
          "unique": false
        },
        {
          "columnNames": ["idx"],
          "composite": false,
          "keyName": "service_idx_index",
          "constraint": false,
          "primary": false,
          "unique": false
        },
        {
          "columnNames": ["is_deleted"],
          "composite": false,
          "keyName": "service_is_deleted_index",
          "constraint": false,
          "primary": false,
          "unique": false
        },
        {
          "columnNames": ["deleted_at"],
          "composite": false,
          "keyName": "service_deleted_at_index",
          "constraint": false,
          "primary": false,
          "unique": false
        },
        {
          "columnNames": ["name"],
          "composite": false,
          "keyName": "service_name_index",
          "constraint": false,
          "primary": false,
          "unique": false
        },
        {
          "columnNames": ["description"],
          "composite": false,
          "keyName": "service_description_index",
          "constraint": false,
          "primary": false,
          "unique": false
        },
        {
          "keyName": "service_pkey",
          "columnNames": ["id"],
          "composite": false,
          "constraint": true,
          "primary": true,
          "unique": true
        }
      ],
      "checks": [],
      "foreignKeys": {
        "service_type_id_foreign": {
          "constraintName": "service_type_id_foreign",
          "columnNames": ["type_id"],
          "localTableName": "public.service",
          "referencedColumnNames": ["id"],
          "referencedTableName": "public.service_type",
          "updateRule": "cascade"
        },
        "service_user_id_foreign": {
          "constraintName": "service_user_id_foreign",
          "columnNames": ["user_id"],
          "localTableName": "public.service",
          "referencedColumnNames": ["id"],
          "referencedTableName": "public.user",
          "updateRule": "cascade"
        }
      },
      "nativeEnums": {}
    },
    {
      "columns": {
        "id": {
          "name": "id",
          "type": "serial",
          "unsigned": true,
          "autoincrement": true,
          "primary": true,
          "nullable": false,
          "mappedType": "integer"
        },
        "structure_id": {
          "name": "structure_id",
          "type": "int",
          "unsigned": false,
          "autoincrement": false,
          "primary": false,
          "nullable": false,
          "mappedType": "integer"
        },
        "service_id": {
          "name": "service_id",
          "type": "int",
          "unsigned": false,
          "autoincrement": false,
          "primary": false,
          "nullable": false,
          "mappedType": "integer"
        }
      },
      "name": "structure_services",
      "schema": "public",
      "indexes": [
        {
          "keyName": "structure_services_pkey",
          "columnNames": ["id"],
          "composite": false,
          "constraint": true,
          "primary": true,
          "unique": true
        }
      ],
      "checks": [],
      "foreignKeys": {
        "structure_services_structure_id_foreign": {
          "constraintName": "structure_services_structure_id_foreign",
          "columnNames": ["structure_id"],
          "localTableName": "public.structure_services",
          "referencedColumnNames": ["id"],
          "referencedTableName": "public.structure",
          "deleteRule": "cascade",
          "updateRule": "cascade"
        },
        "structure_services_service_id_foreign": {
          "constraintName": "structure_services_service_id_foreign",
          "columnNames": ["service_id"],
          "localTableName": "public.structure_services",
          "referencedColumnNames": ["id"],
          "referencedTableName": "public.service",
          "deleteRule": "cascade",
          "updateRule": "cascade"
        }
      },
      "nativeEnums": {}
    },
    {
      "columns": {
        "service_id": {
          "name": "service_id",
          "type": "int",
          "unsigned": false,
          "autoincrement": false,
          "primary": false,
          "nullable": false,
          "mappedType": "integer"
        },
        "setting_id": {
          "name": "setting_id",
          "type": "int",
          "unsigned": false,
          "autoincrement": false,
          "primary": false,
          "nullable": false,
          "mappedType": "integer"
        }
      },
      "name": "service_settings",
      "schema": "public",
      "indexes": [
        {
          "keyName": "service_settings_pkey",
          "columnNames": ["service_id", "setting_id"],
          "composite": true,
          "constraint": true,
          "primary": true,
          "unique": true
        }
      ],
      "checks": [],
      "foreignKeys": {
        "service_settings_service_id_foreign": {
          "constraintName": "service_settings_service_id_foreign",
          "columnNames": ["service_id"],
          "localTableName": "public.service_settings",
          "referencedColumnNames": ["id"],
          "referencedTableName": "public.service",
          "deleteRule": "cascade",
          "updateRule": "cascade"
        },
        "service_settings_setting_id_foreign": {
          "constraintName": "service_settings_setting_id_foreign",
          "columnNames": ["setting_id"],
          "localTableName": "public.service_settings",
          "referencedColumnNames": ["id"],
          "referencedTableName": "public.setting",
          "deleteRule": "cascade",
          "updateRule": "cascade"
        }
      },
      "nativeEnums": {}
    },
    {
      "columns": {
        "service_id": {
          "name": "service_id",
          "type": "int",
          "unsigned": false,
          "autoincrement": false,
          "primary": false,
          "nullable": false,
          "mappedType": "integer"
        },
        "role_id": {
          "name": "role_id",
          "type": "int",
          "unsigned": false,
          "autoincrement": false,
          "primary": false,
          "nullable": false,
          "mappedType": "integer"
        }
      },
      "name": "service_roles",
      "schema": "public",
      "indexes": [
        {
          "keyName": "service_roles_pkey",
          "columnNames": ["service_id", "role_id"],
          "composite": true,
          "constraint": true,
          "primary": true,
          "unique": true
        }
      ],
      "checks": [],
      "foreignKeys": {
        "service_roles_service_id_foreign": {
          "constraintName": "service_roles_service_id_foreign",
          "columnNames": ["service_id"],
          "localTableName": "public.service_roles",
          "referencedColumnNames": ["id"],
          "referencedTableName": "public.service",
          "deleteRule": "cascade",
          "updateRule": "cascade"
        },
        "service_roles_role_id_foreign": {
          "constraintName": "service_roles_role_id_foreign",
          "columnNames": ["role_id"],
          "localTableName": "public.service_roles",
          "referencedColumnNames": ["id"],
          "referencedTableName": "public.role",
          "deleteRule": "cascade",
          "updateRule": "cascade"
        }
      },
      "nativeEnums": {}
    },
    {
      "columns": {
        "id": {
          "name": "id",
          "type": "serial",
          "unsigned": true,
          "autoincrement": true,
          "primary": true,
          "nullable": false,
          "mappedType": "integer"
        },
        "service_1_id": {
          "name": "service_1_id",
          "type": "int",
          "unsigned": false,
          "autoincrement": false,
          "primary": false,
          "nullable": false,
          "mappedType": "integer"
        },
        "service_2_id": {
          "name": "service_2_id",
          "type": "int",
          "unsigned": false,
          "autoincrement": false,
          "primary": false,
          "nullable": false,
          "mappedType": "integer"
        }
      },
      "name": "service_descendants",
      "schema": "public",
      "indexes": [
        {
          "keyName": "service_descendants_pkey",
          "columnNames": ["id"],
          "composite": false,
          "constraint": true,
          "primary": true,
          "unique": true
        }
      ],
      "checks": [],
      "foreignKeys": {
        "service_descendants_service_1_id_foreign": {
          "constraintName": "service_descendants_service_1_id_foreign",
          "columnNames": ["service_1_id"],
          "localTableName": "public.service_descendants",
          "referencedColumnNames": ["id"],
          "referencedTableName": "public.service",
          "deleteRule": "cascade",
          "updateRule": "cascade"
        },
        "service_descendants_service_2_id_foreign": {
          "constraintName": "service_descendants_service_2_id_foreign",
          "columnNames": ["service_2_id"],
          "localTableName": "public.service_descendants",
          "referencedColumnNames": ["id"],
          "referencedTableName": "public.service",
          "deleteRule": "cascade",
          "updateRule": "cascade"
        }
      },
      "nativeEnums": {}
    },
    {
      "columns": {
        "id": {
          "name": "id",
          "type": "serial",
          "unsigned": true,
          "autoincrement": true,
          "primary": true,
          "nullable": false,
          "mappedType": "integer"
        },
        "created_at": {
          "name": "created_at",
          "type": "timestamptz",
          "unsigned": false,
          "autoincrement": false,
          "primary": false,
          "nullable": false,
          "length": 6,
          "mappedType": "datetime"
        },
        "updated_at": {
          "name": "updated_at",
          "type": "timestamptz",
          "unsigned": false,
          "autoincrement": false,
          "primary": false,
          "nullable": false,
          "length": 6,
          "mappedType": "datetime"
        },
        "idx": {
          "name": "idx",
          "type": "varchar(255)",
          "unsigned": false,
          "autoincrement": false,
          "primary": false,
          "nullable": false,
          "mappedType": "string"
        },
        "revision": {
          "name": "revision",
          "type": "int",
          "unsigned": false,
          "autoincrement": false,
          "primary": false,
          "nullable": false,
          "default": "0",
          "mappedType": "integer"
        },
        "is_deleted": {
          "name": "is_deleted",
          "type": "boolean",
          "unsigned": false,
          "autoincrement": false,
          "primary": false,
          "nullable": false,
          "default": "false",
          "mappedType": "boolean"
        },
        "deleted_at": {
          "name": "deleted_at",
          "type": "timestamptz",
          "unsigned": false,
          "autoincrement": false,
          "primary": false,
          "nullable": true,
          "length": 6,
          "default": "null",
          "mappedType": "datetime"
        },
        "name": {
          "name": "name",
          "type": "varchar(255)",
          "unsigned": false,
          "autoincrement": false,
          "primary": false,
          "nullable": false,
          "mappedType": "string"
        },
        "user_id": {
          "name": "user_id",
          "type": "int",
          "unsigned": false,
          "autoincrement": false,
          "primary": false,
          "nullable": false,
          "mappedType": "integer"
        }
      },
      "name": "file",
      "schema": "public",
      "indexes": [
        {
          "columnNames": ["id"],
          "composite": false,
          "keyName": "file_id_index",
          "constraint": false,
          "primary": false,
          "unique": false
        },
        {
          "columnNames": ["idx"],
          "composite": false,
          "keyName": "file_idx_index",
          "constraint": false,
          "primary": false,
          "unique": false
        },
        {
          "columnNames": ["is_deleted"],
          "composite": false,
          "keyName": "file_is_deleted_index",
          "constraint": false,
          "primary": false,
          "unique": false
        },
        {
          "columnNames": ["deleted_at"],
          "composite": false,
          "keyName": "file_deleted_at_index",
          "constraint": false,
          "primary": false,
          "unique": false
        },
        {
          "columnNames": ["name"],
          "composite": false,
          "keyName": "file_name_index",
          "constraint": false,
          "primary": false,
          "unique": false
        },
        {
          "keyName": "file_name_unique",
          "columnNames": ["name"],
          "composite": false,
          "constraint": true,
          "primary": false,
          "unique": true
        },
        {
          "keyName": "file_pkey",
          "columnNames": ["id"],
          "composite": false,
          "constraint": true,
          "primary": true,
          "unique": true
        }
      ],
      "checks": [],
      "foreignKeys": {
        "file_user_id_foreign": {
          "constraintName": "file_user_id_foreign",
          "columnNames": ["user_id"],
          "localTableName": "public.file",
          "referencedColumnNames": ["id"],
          "referencedTableName": "public.user",
          "updateRule": "cascade"
        }
      },
      "nativeEnums": {}
    },
    {
      "columns": {
        "id": {
          "name": "id",
          "type": "serial",
          "unsigned": true,
          "autoincrement": true,
          "primary": true,
          "nullable": false,
          "mappedType": "integer"
        },
        "created_at": {
          "name": "created_at",
          "type": "timestamptz",
          "unsigned": false,
          "autoincrement": false,
          "primary": false,
          "nullable": false,
          "length": 6,
          "mappedType": "datetime"
        },
        "updated_at": {
          "name": "updated_at",
          "type": "timestamptz",
          "unsigned": false,
          "autoincrement": false,
          "primary": false,
          "nullable": false,
          "length": 6,
          "mappedType": "datetime"
        },
        "idx": {
          "name": "idx",
          "type": "varchar(255)",
          "unsigned": false,
          "autoincrement": false,
          "primary": false,
          "nullable": false,
          "mappedType": "string"
        },
        "revision": {
          "name": "revision",
          "type": "int",
          "unsigned": false,
          "autoincrement": false,
          "primary": false,
          "nullable": false,
          "default": "0",
          "mappedType": "integer"
        },
        "is_deleted": {
          "name": "is_deleted",
          "type": "boolean",
          "unsigned": false,
          "autoincrement": false,
          "primary": false,
          "nullable": false,
          "default": "false",
          "mappedType": "boolean"
        },
        "deleted_at": {
          "name": "deleted_at",
          "type": "timestamptz",
          "unsigned": false,
          "autoincrement": false,
          "primary": false,
          "nullable": true,
          "length": 6,
          "default": "null",
          "mappedType": "datetime"
        },
        "name": {
          "name": "name",
          "type": "varchar(255)",
          "unsigned": false,
          "autoincrement": false,
          "primary": false,
          "nullable": false,
          "mappedType": "string"
        },
        "description": {
          "name": "description",
          "type": "varchar(255)",
          "unsigned": false,
          "autoincrement": false,
          "primary": false,
          "nullable": false,
          "mappedType": "string"
        },
        "user_id": {
          "name": "user_id",
          "type": "int",
          "unsigned": false,
          "autoincrement": false,
          "primary": false,
          "nullable": false,
          "mappedType": "integer"
        }
      },
      "name": "component",
      "schema": "public",
      "indexes": [
        {
          "columnNames": ["id"],
          "composite": false,
          "keyName": "component_id_index",
          "constraint": false,
          "primary": false,
          "unique": false
        },
        {
          "columnNames": ["idx"],
          "composite": false,
          "keyName": "component_idx_index",
          "constraint": false,
          "primary": false,
          "unique": false
        },
        {
          "columnNames": ["is_deleted"],
          "composite": false,
          "keyName": "component_is_deleted_index",
          "constraint": false,
          "primary": false,
          "unique": false
        },
        {
          "columnNames": ["deleted_at"],
          "composite": false,
          "keyName": "component_deleted_at_index",
          "constraint": false,
          "primary": false,
          "unique": false
        },
        {
          "columnNames": ["name"],
          "composite": false,
          "keyName": "component_name_unique",
          "constraint": true,
          "primary": false,
          "unique": true
        },
        {
          "keyName": "component_pkey",
          "columnNames": ["id"],
          "composite": false,
          "constraint": true,
          "primary": true,
          "unique": true
        }
      ],
      "checks": [],
      "foreignKeys": {
        "component_user_id_foreign": {
          "constraintName": "component_user_id_foreign",
          "columnNames": ["user_id"],
          "localTableName": "public.component",
          "referencedColumnNames": ["id"],
          "referencedTableName": "public.user",
          "updateRule": "cascade"
        }
      },
      "nativeEnums": {}
    },
    {
      "columns": {
        "component_id": {
          "name": "component_id",
          "type": "int",
          "unsigned": false,
          "autoincrement": false,
          "primary": false,
          "nullable": false,
          "mappedType": "integer"
        },
        "file_id": {
          "name": "file_id",
          "type": "int",
          "unsigned": false,
          "autoincrement": false,
          "primary": false,
          "nullable": false,
          "mappedType": "integer"
        }
      },
      "name": "component_files",
      "schema": "public",
      "indexes": [
        {
          "keyName": "component_files_pkey",
          "columnNames": ["component_id", "file_id"],
          "composite": true,
          "constraint": true,
          "primary": true,
          "unique": true
        }
      ],
      "checks": [],
      "foreignKeys": {
        "component_files_component_id_foreign": {
          "constraintName": "component_files_component_id_foreign",
          "columnNames": ["component_id"],
          "localTableName": "public.component_files",
          "referencedColumnNames": ["id"],
          "referencedTableName": "public.component",
          "deleteRule": "cascade",
          "updateRule": "cascade"
        },
        "component_files_file_id_foreign": {
          "constraintName": "component_files_file_id_foreign",
          "columnNames": ["file_id"],
          "localTableName": "public.component_files",
          "referencedColumnNames": ["id"],
          "referencedTableName": "public.file",
          "deleteRule": "cascade",
          "updateRule": "cascade"
        }
      },
      "nativeEnums": {}
    }
  ],
  "nativeEnums": {}
}
